{"data": [{"url": "http://thinkhazard.org/en/report/57-colombia", "admin0": "Colombia", "code": 57}, {"admin1": "Sao Paulo", "admin0": "Brazil", "url": "http://thinkhazard.org/en/report/11115-brazil-sao-paulo-colombia", "code": 11115, "admin2": "Colombia"}, {"admin1": "Huila", "admin0": "Colombia", "url": "http://thinkhazard.org/en/report/13980-colombia-huila-colombia", "code": 13980, "admin2": "Colombia"}, {"admin1": "Las Tunas", "admin0": "Cuba", "url": "http://thinkhazard.org/en/report/14742-cuba-las-tunas-colombia", "code": 14742, "admin2": "Colombia"}, {"admin1": "Cordillera", "admin0": "Paraguay", "url": "http://thinkhazard.org/en/report/23888-paraguay-cordillera-nueva-colombia", "code": 23888, "admin2": "Nueva Colombia"}, {"admin1": "Atlantico", "admin0": "Colombia", "url": "http://thinkhazard.org/en/report/13487-colombia-atlantico-puerto-colombia", "code": 13487, "admin2": "Puerto Colombia"}, {"admin1": "Guainia", "admin0": "Colombia", "url": "http://thinkhazard.org/en/report/13956-colombia-guainia-puerto-colombia", "code": 13956, "admin2": "Puerto Colombia"}]}